patched_pyper.py
setup.py
patched_pyper.egg-info/PKG-INFO
patched_pyper.egg-info/SOURCES.txt
patched_pyper.egg-info/dependency_links.txt
patched_pyper.egg-info/top_level.txt