Metadata-Version: 1.0
Name: patched-pyper
Version: 1.1.4
Summary: a patched version of pyper for bridging Python to R
Home-page: UNKNOWN
Author: Uwe Schmitt
Author-email: uwe.schmitt@id.ethz.ch
License: BSD
Platform: UNKNOWN
